ExtraTree/__init__.py
ExtraTree/ExtraEnsemble/__init__.py
ExtraTree/ExtraEnsemble/boosting.py
ExtraTree/ExtraEnsemble/forest.py
ExtraTree/ExtraTree/__init__.py
ExtraTree/ExtraTree/_criterion.py
ExtraTree/ExtraTree/_estimator.py
ExtraTree/ExtraTree/_splitter.py
ExtraTree/ExtraTree/_tree.py
ExtraTree/ExtraTree/tree.py
tests/__init__.py
tests/test_boosting_regressor.py
tests/test_forest_regressor.py
tests/test_tree_regresson_info.py
tests/test_tree_regressor.py
tests/test_tree_regressor_cv.py
ExtraTree-0.0.3.dist-info/LICENSE
ExtraTree-0.0.3.dist-info/METADATA
ExtraTree-0.0.3.dist-info/WHEEL
ExtraTree-0.0.3.dist-info/top_level.txt
ExtraTree-0.0.3.dist-info/RECORD
