Metadata-Version: 2.1
Name: ExtraTree
Version: 0.0.3
Summary: Extrapolated Tree
Home-page: https://github.com/Karlmyh/ExtraTree
Author: Yuheng Ma
Author-email: yma@ruc.edu.cn
Classifier: Programming Language :: Python :: 3
Classifier: License :: OSI Approved :: MIT License
Requires-Python: >=3
License-File: LICENSE
Requires-Dist: numpy
Requires-Dist: scikit-learn
Requires-Dist: multiprocess
Requires-Dist: numba
